mdtopptx/__init__.py
mdtopptx/main.py
mdtopptx-0.1.0.dist-info/LICENSE
mdtopptx-0.1.0.dist-info/METADATA
mdtopptx-0.1.0.dist-info/WHEEL
mdtopptx-0.1.0.dist-info/top_level.txt
mdtopptx-0.1.0.dist-info/RECORD
