Metadata-Version: 2.1
Name: mdtopptx
Version: 0.1.0
Summary: Converts markdown files to PowerPoint presentations
License-File: LICENSE
